parallel_docker_build/__init__.py
parallel_docker_build/__metadata__.py
parallel_docker_build/cli.py
parallel_docker_build/tools.py
parallel_docker_build/workflow-schema.yaml
parallel_docker_build-0.3.0.dist-info/LICENSE
parallel_docker_build-0.3.0.dist-info/METADATA
parallel_docker_build-0.3.0.dist-info/WHEEL
parallel_docker_build-0.3.0.dist-info/entry_points.txt
parallel_docker_build-0.3.0.dist-info/top_level.txt
parallel_docker_build-0.3.0.dist-info/RECORD
