Metadata-Version: 2.1
Name: parallel-docker-build
Version: 0.3.0
Summary: parallel_docker_build
Home-page: https://github.com/jccurtis/parallel-docker-build
Author: Joseph (Joey) Curtis
Maintainer: Joseph (Joey) Curtis
License: MIT
Download-URL: https://github.com/jccurtis/parallel-docker-build/-/tags
Keywords: automation docker continuous-deployment
Platform: any
Classifier: Programming Language :: Python :: 3 :: Only
Classifier: Programming Language :: Python :: 3.6
Classifier: Programming Language :: Python :: 3.7
Classifier: Programming Language :: Python :: 3.8
Classifier: Programming Language :: Python :: 3.9
Classifier: Development Status :: 4 - Beta
Classifier: Intended Audience :: Developers
Classifier: Operating System :: OS Independent
Classifier: Natural Language :: English
Classifier: License :: OSI Approved :: MIT License
Requires-Python: >=3.6
License-File: LICENSE
Requires-Dist: docker
Requires-Dist: yamale
